valeriepieris.cpython-310-x86_64-linux-gnu.so
valeriepieris-0.1.26.dist-info/METADATA
valeriepieris-0.1.26.dist-info/WHEEL
valeriepieris-0.1.26.dist-info/RECORD
valeriepieris-0.1.26.dist-info/top_level.txt
valeriepieris-0.1.26.dist-info/LICENSE.txt
valeriepieris/__init__.py
