Metadata-Version: 2.1
Name: valeriepieris
Version: 0.1.26
Summary: Finding valeriepieris circles
Home-page: https://github.com/rudyarthur/valeriepieris
Author: Rudy Arthur
Author-email: rudy.d.arthur@gmail.com
License: GNU GENERAL PUBLIC LICENSE Version 3
Project-URL: Documentation, https://github.com/rudyarthur/valeriepieris
Project-URL: Code, https://github.com/rudyarthur/valeriepieris
Project-URL: Issue tracker, https://github.com/rudyarthur/valeriepieris/issues
Platform: UNKNOWN
Classifier: Development Status :: 1 - Planning
Classifier: License :: OSI Approved :: GNU General Public License v3 (GPLv3)
Classifier: Intended Audience :: Education
Classifier: Intended Audience :: Science/Research
Classifier: Topic :: Scientific/Engineering
Classifier: Topic :: Scientific/Engineering :: Mathematics
Classifier: Natural Language :: English
Classifier: Operating System :: OS Independent
Classifier: Programming Language :: C
Classifier: Programming Language :: Cython
Classifier: Programming Language :: Python
Classifier: Programming Language :: Python :: 3
Classifier: Programming Language :: Python :: 3.4
Classifier: Programming Language :: Python :: 3.5
Classifier: Programming Language :: Python :: 3.6
Classifier: Programming Language :: Python :: 3.7
Classifier: Programming Language :: Python :: 3 :: Only
Classifier: Programming Language :: Python :: Implementation :: CPython
Requires-Python: >=3.9
License-File: LICENSE.txt
Requires-Dist: Cython (>=3.0.10)
Requires-Dist: numpy (>=2.0.0)
